exporimo/__init__.py
exporimo/main.py
exporimo/params.py
exporimo/types.py
exporimo/utils.py
exporimo-0.1.1.dist-info/LICENSE
exporimo-0.1.1.dist-info/METADATA
exporimo-0.1.1.dist-info/WHEEL
exporimo-0.1.1.dist-info/top_level.txt
exporimo-0.1.1.dist-info/RECORD
