Metadata-Version: 2.2
Name: exporimo
Version: 0.1.1
Summary: Library for fast expose marimo notebook to Internet
Home-page: https://github.com/FailProger/exporimo.git
Author: Vyacheslav Pervakov
Author-email: WsrrcalzWehgwmD@protonmail.com
License: MIT License
Project-URL: GitHub, https://github.com/FailProger/exporimo.git
Project-URL: PyPI, https://pypi.org/project/exporimo/
Keywords: Python,marimo
Classifier: Programming Language :: Python :: 3
Classifier: License :: OSI Approved :: MIT License
Requires-Python: >=3.9
License-File: LICENSE
Requires-Dist: marimo>=0.10.0
Dynamic: author
Dynamic: author-email
Dynamic: classifier
Dynamic: description
Dynamic: description-content-type
Dynamic: home-page
Dynamic: keywords
Dynamic: license
Dynamic: project-url
Dynamic: requires-dist
Dynamic: requires-python
Dynamic: summary
